vnpy_qmt/__init__.py
vnpy_qmt/md.py
vnpy_qmt/qmt_gateway.py
vnpy_qmt/td.py
vnpy_qmt/utils.py
vnpy_qmt-0.3.3.dist-info/LICENSE
vnpy_qmt-0.3.3.dist-info/METADATA
vnpy_qmt-0.3.3.dist-info/WHEEL
vnpy_qmt-0.3.3.dist-info/top_level.txt
vnpy_qmt-0.3.3.dist-info/RECORD
