Metadata-Version: 2.1
Name: vnpy-qmt
Version: 0.3.3
Summary: vnpy qmt gateway
Home-page: https://github.com/fsksf/vnpy_qmt
Author: fsksf
Author-email: kangyuqiang123@qq.com
Keywords: vnpy gateway qmt
Classifier: Development Status :: 5 - Production/Stable
Classifier: Intended Audience :: Developers
Classifier: Topic :: Software Development :: Libraries
Classifier: License :: OSI Approved :: Apache Software License
Classifier: Programming Language :: Python :: 3.7
Classifier: Programming Language :: Python :: 3.8
Classifier: Programming Language :: Python :: 3.9
Classifier: Programming Language :: Python :: 3.10
License-File: LICENSE
